border_secure_core/__init__.py
border_secure_core/_py2_core.py
border_secure_core/_py3_core.py
border_secure_core/errors.py
border_secure_core/py2_core.py
border_secure_core/py3_core.py
border_secure_core/utils/__init__.py
border_secure_core/utils/yaml_parser.py
test/__init__.py
border_secure_core-0.2.3.dist-info/METADATA
border_secure_core-0.2.3.dist-info/WHEEL
border_secure_core-0.2.3.dist-info/top_level.txt
border_secure_core-0.2.3.dist-info/RECORD
